{
  "project_info": {
    "project_number": "36546116971",
    "project_id": "furniture-ecomerece",
    "storage_bucket": "furniture-ecomerece.appspot.com"
  },
  "client": [
    {
      "client_info": {
        "mobilesdk_app_id": "1:36546116971:android:aaa4c57e665db7b880602e",
        "android_client_info": {
          "package_name": "com.example.furniturecloudy"
        }
      },
      "oauth_client": [
        {
          "client_id": "36546116971-5n8ekcaos37qinpig3n4f3lck4eafhef.apps.googleusercontent.com",
          "client_type": 1,
          "android_info": {
            "package_name": "com.example.furniturecloudy",
            "certificate_hash": "0af769e4e50d5be18839bc8d658a98613c431b2e"
          }
        },
        {
          "client_id": "36546116971-ok6r4g6gr96vk37g8pf6fvt6ih8l4lqr.apps.googleusercontent.com",
          "client_type": 3
        }
      ],
      "api_key": [
        {
          "current_key": "AIzaSyARIZ-3_QDcP2FAk-It898ohrygOsUCKT4"
        }
      ],
      "services": {
        "appinvite_service": {
          "other_platform_oauth_client": [
            {
              "client_id": "36546116971-ok6r4g6gr96vk37g8pf6fvt6ih8l4lqr.apps.googleusercontent.com",
              "client_type": 3
            }
          ]
        }
      }
    },
    {
      "client_info": {
        "mobilesdk_app_id": "1:36546116971:android:b5353fb437d2620a80602e",
        "android_client_info": {
          "package_name": "com.example.productsadder"
        }
      },
      "oauth_client": [
        {
          "client_id": "36546116971-ok6r4g6gr96vk37g8pf6fvt6ih8l4lqr.apps.googleusercontent.com",
          "client_type": 3
        }
      ],
      "api_key": [
        {
          "current_key": "AIzaSyARIZ-3_QDcP2FAk-It898ohrygOsUCKT4"
        }
      ],
      "services": {
        "appinvite_service": {
          "other_platform_oauth_client": [
            {
              "client_id": "36546116971-ok6r4g6gr96vk37g8pf6fvt6ih8l4lqr.apps.googleusercontent.com",
              "client_type": 3
            }
          ]
        }
      }
    }
  ],
  "configuration_version": "1"
}